draw_paper/__init__.py
draw_paper/config.py
draw_paper/core.py
draw_paper/plots.py
draw_paper/styles.py
draw_paper/templates.py
draw_paper-0.1.2.dist-info/METADATA
draw_paper-0.1.2.dist-info/WHEEL
draw_paper-0.1.2.dist-info/RECORD
